{
  "name": "Nerps-For-Foundry",
  "title": "Nerps For Foundry",
  "description": "A module for personal use across our campaigns",
  "authors": [
    {
      "name": "JamzTheMan",
      "url": "https://github.com/JamzTheMan",
      "discord": "Jamz#7942"
    }
  ],
  "url": "https://github.com/JamzTheMan/Nerps-For-Foundry",
  "flags": {},
  "version": "3.1.1",
  "minimumCoreVersion": 9,
  "compatibleCoreVersion": 9,
  "scripts": [],
  "esmodules": [
    "/scripts/nerps-for-foundry.js",
    "/scripts/hooks-for-nerps.js"
  ],
  "styles": [
    "/styles/nerps-for-foundry.css"
  ],
  "languages": [
    {
      "lang": "en",
      "name": "English",
      "path": "languages/en.json"
    }
  ],
  "packs": [
    {
      "name": "shared-items",
      "label": "Shared Items",
      "path": "./packs/shared-items.db",
      "entity": "Item",
      "type": "Item",
      "private": false
    },
    {
      "name": "shared-creatures",
      "label": "Shared Creatures",
      "path": "./packs/shared-creatures.db",
      "entity": "Actor",
      "type": "Actor",
      "private": false
    },
    {
      "name": "shared-scenes",
      "label": "Shared Scenes",
      "path": "./packs/shared-scenes.db",
      "entity": "Scene",
      "type": "Scene",
      "private": false
    },
    {
      "name": "shared-journal-entries",
      "label": "Shared Journal Entries",
      "path": "./packs/shared-journal-entries.db",
      "entity": "JournalEntry",
      "type": "JournalEntry",
      "private": false
    },
    {
      "name": "shared-macros",
      "label": "Shared Macros",
      "path": "./packs/shared-macros.db",
      "entity": "Macro",
      "type": "Macro",
      "private": false
    },
    {
      "name": "shared-roll-tables",
      "label": "Shared Roll Tables",
      "path": "./packs/shared-roll-tables.db",
      "entity": "RollTable",
      "type": "RollTable",
      "private": false
    },
    {
      "name": "shared-playlists",
      "label": "Shared Playlists",
      "path": "./packs/shared-playlists.db",
      "entity": "Playlist",
      "type": "Playlist",
      "private": false
    }
  ],
  "system": [],
  "dependencies": [
    {
      "name": "pf2e",
      "type": "system"
    },
    {
      "name": "socketlib",
      "manifest": "https://raw.githubusercontent.com/manuelVo/foundryvtt-socketlib/master/module.json",
      "type": "module"
    }
  ],
  "socket": true,
  "manifest": "https://github.com/JamzTheMan/Nerps-For-Foundry/releases/latest/download/module.json",
  "download": "https://github.com/JamzTheMan/Nerps-For-Foundry/releases/download/latest/module.zip",
  "protected": false,
  "coreTranslation": false,
  "library": "false"
}